README.md
setup.py
dllib/__init__.py
dllib/data.py
dllib/io.py
dllib/network.py
dllib/sys.py
dllib/viz.py
fuqichen.egg-info/PKG-INFO
fuqichen.egg-info/SOURCES.txt
fuqichen.egg-info/dependency_links.txt
fuqichen.egg-info/not-zip-safe
fuqichen.egg-info/requires.txt
fuqichen.egg-info/top_level.txt