Metadata-Version: 1.0
Name: fuqichen
Version: 0.0.5
Summary: A custom deep learning lib
Home-page: https://github.com/fuqichen1998/dllib
Author: Qichen Fu
Author-email: fuqichen1998@gmail.com
License: MIT
Platform: UNKNOWN
